{
  "nm": "Attachment#1",
  "ddd": 0,
  "h": 480,
  "w": 480,
  "meta": {
    "g": "@lottiefiles/toolkit-js 0.26.1"
  },
  "layers": [
    {
      "ty": 3,
      "nm": "Null 3",
      "sr": 1,
      "st": 0,
      "op": 302,
      "ip": 0,
      "hd": false,
      "ddd": 0,
      "bm": 0,
      "hasMask": false,
      "ao": 0,
      "ks": {
        "a": {
          "a": 0,
          "k": [
            0,
            0,
            0
          ],
          "ix": 1
        },
        "s": {
          "a": 0,
          "k": [
            100,
            100,
            100
          ],
          "ix": 6
        },
        "sk": {
          "a": 0,
          "k": 0
        },
        "p": {
          "a": 0,
          "k": [
            240,
            240,
            0
          ],
          "ix": 2
        },
        "r": {
          "a": 1,
          "k": [
            {
              "o": {
                "x": 0.59,
                "y": 0
              },
              "i": {
                "x": 0.855,
                "y": 0.632
              },
              "s": [
                0
              ],
              "t": 0
            },
            {
              "o": {
                "x": 0.117,
                "y": 0.374
              },
              "i": {
                "x": -0.062,
                "y": 1
              },
              "s": [
                -45
              ],
              "t": 61.668
            },
            {
              "s": [
                -180
              ],
              "t": 293.33203125
            }
          ],
          "ix": 10
        },
        "sa": {
          "a": 0,
          "k": 0
        },
        "o": {
          "a": 0,
          "k": 0,
          "ix": 11
        }
      },
      "ef": [],
      "ind": 1
    },
    {
      "ty": 4,
      "nm": "TOP",
      "sr": 1,
      "st": 0,
      "op": 302,
      "ip": 0,
      "hd": false,
      "ddd": 0,
      "bm": 0,
      "hasMask": false,
      "ao": 0,
      "ks": {
        "a": {
          "a": 0,
          "k": [
            12,
            12,
            0
          ],
          "ix": 1
        },
        "s": {
          "a": 0,
          "k": [
            2000,
            2000,
            100
          ],
          "ix": 6
        },
        "sk": {
          "a": 0,
          "k": 0
        },
        "p": {
          "a": 1,
          "k": [
            {
              "o": {
                "x": 0.333,
                "y": 0
              },
              "i": {
                "x": 0,
                "y": 1
              },
              "s": [
                0,
                0,
                0
              ],
              "t": 0,
              "ti": [
                11.833,
                -11.833,
                0
              ],
              "to": [
                -11.833,
                11.833,
                0
              ]
            },
            {
              "o": {
                "x": 0.167,
                "y": 0.167
              },
              "i": {
                "x": 0,
                "y": 0
              },
              "s": [
                -71,
                71,
                0
              ],
              "t": 61.668,
              "ti": [
                0,
                0,
                0
              ],
              "to": [
                0,
                0,
                0
              ]
            },
            {
              "o": {
                "x": 0.167,
                "y": 0
              },
              "i": {
                "x": 0,
                "y": 1
              },
              "s": [
                -71,
                71,
                0
              ],
              "t": 156.668,
              "ti": [
                -11.833,
                11.833,
                0
              ],
              "to": [
                11.833,
                -11.833,
                0
              ]
            },
            {
              "s": [
                0,
                0,
                0
              ],
              "t": 293.33203125
            }
          ],
          "ix": 2
        },
        "r": {
          "a": 0,
          "k": 0,
          "ix": 10
        },
        "sa": {
          "a": 0,
          "k": 0
        },
        "o": {
          "a": 1,
          "k": [
            {
              "o": {
                "x": 0.333,
                "y": 0
              },
              "i": {
                "x": 0,
                "y": 1
              },
              "s": [
                100
              ],
              "t": 156.668
            },
            {
              "s": [
                40
              ],
              "t": 293.33203125
            }
          ],
          "ix": 11
        }
      },
      "ef": [],
      "shapes": [
        {
          "ty": "gr",
          "bm": 0,
          "hd": false,
          "mn": "ADBE Vector Group",
          "nm": "Group 1",
          "ix": 1,
          "cix": 2,
          "np": 3,
          "it": [
            {
              "ty": "sh",
              "bm": 0,
              "hd": false,
              "mn": "ADBE Vector Shape - Group",
              "nm": "Path 2",
              "ix": 1,
              "d": 1,
              "ks": {
                "a": 0,
                "k": {
                  "c": true,
                  "i": [
                    [
                      0,
                      0
                    ],
                    [
                      0,
                      0
                    ],
                    [
                      0.391,
                      0.391
                    ],
                    [
                      0.391,
                      -0.391
                    ],
                    [
                      0,
                      0
                    ],
                    [
                      0,
                      0
                    ],
                    [
                      -0.781,
                      0.781
                    ],
                    [
                      0,
                      0
                    ],
                    [
                      -0.781,
                      -0.781
                    ],
                    [
                      0,
                      0
                    ],
                    [
                      0.781,
                      -0.781
                    ],
                    [
                      0,
                      0
                    ],
                    [
                      0.781,
                      0.781
                    ]
                  ],
                  "o": [
                    [
                      0,
                      0
                    ],
                    [
                      0.391,
                      -0.391
                    ],
                    [
                      -0.391,
                      -0.391
                    ],
                    [
                      0,
                      0
                    ],
                    [
                      0,
                      0
                    ],
                    [
                      -0.781,
                      -0.781
                    ],
                    [
                      0,
                      0
                    ],
                    [
                      0.781,
                      -0.781
                    ],
                    [
                      0,
                      0
                    ],
                    [
                      0.781,
                      0.781
                    ],
                    [
                      0,
                      0
                    ],
                    [
                      -0.781,
                      0.781
                    ],
                    [
                      0,
                      0
                    ]
                  ],
                  "v": [
                    [
                      -2.121,
                      3.536
                    ],
                    [
                      0,
                      1.414
                    ],
                    [
                      0,
                      0
                    ],
                    [
                      -1.414,
                      0
                    ],
                    [
                      -3.536,
                      2.121
                    ],
                    [
                      -4.243,
                      1.414
                    ],
                    [
                      -4.243,
                      -1.414
                    ],
                    [
                      -1.414,
                      -4.243
                    ],
                    [
                      1.414,
                      -4.243
                    ],
                    [
                      4.243,
                      -1.414
                    ],
                    [
                      4.243,
                      1.414
                    ],
                    [
                      1.414,
                      4.243
                    ],
                    [
                      -1.414,
                      4.243
                    ]
                  ]
                },
                "ix": 2
              }
            },
            {
              "ty": "mm",
              "bm": 0,
              "hd": false,
              "mn": "ADBE Vector Filter - Merge",
              "nm": "Merge Paths 1",
              "mm": 4
            },
            {
              "ty": "fl",
              "bm": 0,
              "hd": false,
              "mn": "ADBE Vector Graphic - Fill",
              "nm": "Fill 1",
              "c": {
                "a": 0,
                "k": [
                  0.9725,
                  0.8431,
                  0.3961
                ],
                "ix": 4
              },
              "r": 1,
              "o": {
                "a": 0,
                "k": 100,
                "ix": 5
              }
            },
            {
              "ty": "tr",
              "a": {
                "a": 0,
                "k": [
                  0,
                  0
                ],
                "ix": 1
              },
              "s": {
                "a": 0,
                "k": [
                  100,
                  100
                ],
                "ix": 3
              },
              "sk": {
                "a": 0,
                "k": 0,
                "ix": 4
              },
              "p": {
                "a": 0,
                "k": [
                  15.536,
                  8.464
                ],
                "ix": 2
              },
              "r": {
                "a": 0,
                "k": 0,
                "ix": 6
              },
              "sa": {
                "a": 0,
                "k": 0,
                "ix": 5
              },
              "o": {
                "a": 0,
                "k": 100,
                "ix": 7
              }
            }
          ]
        }
      ],
      "ind": 2,
      "parent": 1
    },
    {
      "ty": 4,
      "nm": "Attachment#1 Outlines",
      "sr": 1,
      "st": 0,
      "op": 302,
      "ip": 0,
      "hd": false,
      "ln": "1",
      "ddd": 0,
      "bm": 0,
      "hasMask": false,
      "ao": 0,
      "ks": {
        "a": {
          "a": 0,
          "k": [
            12,
            12,
            0
          ],
          "ix": 1
        },
        "s": {
          "a": 0,
          "k": [
            2000,
            2000,
            100
          ],
          "ix": 6
        },
        "sk": {
          "a": 0,
          "k": 0
        },
        "p": {
          "a": 1,
          "k": [
            {
              "o": {
                "x": 0.333,
                "y": 0
              },
              "i": {
                "x": 0,
                "y": 1
              },
              "s": [
                0,
                0,
                0
              ],
              "t": 0,
              "ti": [
                -11.835,
                11.677,
                0
              ],
              "to": [
                11.835,
                -11.677,
                0
              ]
            },
            {
              "o": {
                "x": 0.167,
                "y": 0.167
              },
              "i": {
                "x": 0,
                "y": 0
              },
              "s": [
                71.012,
                -70.061,
                0
              ],
              "t": 61.668,
              "ti": [
                0,
                0,
                0
              ],
              "to": [
                0,
                0,
                0
              ]
            },
            {
              "o": {
                "x": 0.167,
                "y": 0
              },
              "i": {
                "x": 0,
                "y": 1
              },
              "s": [
                71.012,
                -70.061,
                0
              ],
              "t": 156.668,
              "ti": [
                11.835,
                -11.677,
                0
              ],
              "to": [
                -11.835,
                11.677,
                0
              ]
            },
            {
              "s": [
                0,
                0,
                0
              ],
              "t": 293.33203125
            }
          ],
          "ix": 2
        },
        "r": {
          "a": 0,
          "k": 0,
          "ix": 10
        },
        "sa": {
          "a": 0,
          "k": 0
        },
        "o": {
          "a": 1,
          "k": [
            {
              "o": {
                "x": 0.333,
                "y": 0
              },
              "i": {
                "x": 0,
                "y": 1
              },
              "s": [
                40
              ],
              "t": 0
            },
            {
              "s": [
                100
              ],
              "t": 156.66796875
            }
          ],
          "ix": 11
        }
      },
      "ef": [],
      "shapes": [
        {
          "ty": "gr",
          "bm": 0,
          "hd": false,
          "mn": "ADBE Vector Group",
          "nm": "Group 2",
          "ix": 1,
          "cix": 2,
          "np": 3,
          "it": [
            {
              "ty": "sh",
              "bm": 0,
              "hd": false,
              "mn": "ADBE Vector Shape - Group",
              "nm": "Path 2",
              "ix": 1,
              "d": 1,
              "ks": {
                "a": 0,
                "k": {
                  "c": true,
                  "i": [
                    [
                      0,
                      0
                    ],
                    [
                      0,
                      0
                    ],
                    [
                      -0.391,
                      -0.391
                    ],
                    [
                      -0.391,
                      0.391
                    ],
                    [
                      0,
                      0
                    ],
                    [
                      0,
                      0
                    ],
                    [
                      0.781,
                      -0.781
                    ],
                    [
                      0,
                      0
                    ],
                    [
                      0.781,
                      0.781
                    ],
                    [
                      0,
                      0
                    ],
                    [
                      -0.781,
                      0.781
                    ],
                    [
                      0,
                      0
                    ],
                    [
                      -0.781,
                      -0.781
                    ]
                  ],
                  "o": [
                    [
                      0,
                      0
                    ],
                    [
                      -0.391,
                      0.391
                    ],
                    [
                      0.391,
                      0.391
                    ],
                    [
                      0,
                      0
                    ],
                    [
                      0,
                      0
                    ],
                    [
                      0.781,
                      0.781
                    ],
                    [
                      0,
                      0
                    ],
                    [
                      -0.781,
                      0.781
                    ],
                    [
                      0,
                      0
                    ],
                    [
                      -0.781,
                      -0.781
                    ],
                    [
                      0,
                      0
                    ],
                    [
                      0.781,
                      -0.781
                    ],
                    [
                      0,
                      0
                    ]
                  ],
                  "v": [
                    [
                      2.121,
                      -3.536
                    ],
                    [
                      0,
                      -1.414
                    ],
                    [
                      0,
                      0
                    ],
                    [
                      1.414,
                      0
                    ],
                    [
                      3.536,
                      -2.121
                    ],
                    [
                      4.243,
                      -1.414
                    ],
                    [
                      4.243,
                      1.414
                    ],
                    [
                      1.414,
                      4.243
                    ],
                    [
                      -1.414,
                      4.243
                    ],
                    [
                      -4.243,
                      1.414
                    ],
                    [
                      -4.243,
                      -1.414
                    ],
                    [
                      -1.414,
                      -4.243
                    ],
                    [
                      1.414,
                      -4.243
                    ]
                  ]
                },
                "ix": 2
              }
            },
            {
              "ty": "mm",
              "bm": 0,
              "hd": false,
              "mn": "ADBE Vector Filter - Merge",
              "nm": "Merge Paths 1",
              "mm": 4
            },
            {
              "ty": "fl",
              "bm": 0,
              "hd": false,
              "mn": "ADBE Vector Graphic - Fill",
              "nm": "Fill 1",
              "c": {
                "a": 0,
                "k": [
                  0,
                  0,
                  0
                ],
                "ix": 4
              },
              "r": 1,
              "o": {
                "a": 0,
                "k": 100,
                "ix": 5
              }
            },
            {
              "ty": "tr",
              "a": {
                "a": 0,
                "k": [
                  0,
                  0
                ],
                "ix": 1
              },
              "s": {
                "a": 0,
                "k": [
                  100,
                  100
                ],
                "ix": 3
              },
              "sk": {
                "a": 0,
                "k": 0,
                "ix": 4
              },
              "p": {
                "a": 0,
                "k": [
                  8.464,
                  15.536
                ],
                "ix": 2
              },
              "r": {
                "a": 0,
                "k": 0,
                "ix": 6
              },
              "sa": {
                "a": 0,
                "k": 0,
                "ix": 5
              },
              "o": {
                "a": 0,
                "k": 100,
                "ix": 7
              }
            }
          ]
        }
      ],
      "ind": 3,
      "parent": 1
    },
    {
      "ty": 4,
      "nm": "Shape Layer 1",
      "sr": 1,
      "st": 143,
      "op": 302,
      "ip": 143,
      "hd": false,
      "ddd": 0,
      "bm": 0,
      "hasMask": false,
      "ao": 0,
      "ks": {
        "a": {
          "a": 0,
          "k": [
            -9.5,
            80.5,
            0
          ],
          "ix": 1
        },
        "s": {
          "a": 1,
          "k": [
            {
              "o": {
                "x": 0.333,
                "y": 0
              },
              "i": {
                "x": 0,
                "y": 1
              },
              "s": [
                0,
                0,
                100
              ],
              "t": 143
            },
            {
              "s": [
                183,
                183,
                100
              ],
              "t": 242
            }
          ],
          "ix": 6
        },
        "sk": {
          "a": 0,
          "k": 0
        },
        "p": {
          "a": 0,
          "k": [
            240,
            240,
            0
          ],
          "ix": 2
        },
        "r": {
          "a": 0,
          "k": 0,
          "ix": 10
        },
        "sa": {
          "a": 0,
          "k": 0
        },
        "o": {
          "a": 1,
          "k": [
            {
              "o": {
                "x": 0.333,
                "y": 0
              },
              "i": {
                "x": 0,
                "y": 1
              },
              "s": [
                100
              ],
              "t": 143
            },
            {
              "s": [
                0
              ],
              "t": 242
            }
          ],
          "ix": 11
        }
      },
      "ef": [],
      "shapes": [
        {
          "ty": "gr",
          "bm": 0,
          "hd": false,
          "mn": "ADBE Vector Group",
          "nm": "Ellipse 1",
          "ix": 1,
          "cix": 2,
          "np": 3,
          "it": [
            {
              "ty": "el",
              "bm": 0,
              "hd": false,
              "mn": "ADBE Vector Shape - Ellipse",
              "nm": "Ellipse Path 1",
              "d": 1,
              "p": {
                "a": 0,
                "k": [
                  0,
                  0
                ],
                "ix": 3
              },
              "s": {
                "a": 0,
                "k": [
                  243,
                  243
                ],
                "ix": 2
              }
            },
            {
              "ty": "st",
              "bm": 0,
              "hd": false,
              "mn": "ADBE Vector Graphic - Stroke",
              "nm": "Stroke 1",
              "lc": 1,
              "lj": 1,
              "ml": 4,
              "o": {
                "a": 0,
                "k": 100,
                "ix": 4
              },
              "w": {
                "a": 0,
                "k": 0,
                "ix": 5
              },
              "c": {
                "a": 0,
                "k": [
                  0.8196,
                  0.0314,
                  0.0314
                ],
                "ix": 3
              }
            },
            {
              "ty": "fl",
              "bm": 0,
              "hd": false,
              "mn": "ADBE Vector Graphic - Fill",
              "nm": "Fill 1",
              "c": {
                "a": 0,
                "k": [
                  0,
                  0,
                  0
                ],
                "ix": 4
              },
              "r": 1,
              "o": {
                "a": 0,
                "k": 100,
                "ix": 5
              }
            },
            {
              "ty": "tr",
              "a": {
                "a": 0,
                "k": [
                  0,
                  0
                ],
                "ix": 1
              },
              "s": {
                "a": 0,
                "k": [
                  100,
                  100
                ],
                "ix": 3
              },
              "sk": {
                "a": 0,
                "k": 0,
                "ix": 4
              },
              "p": {
                "a": 0,
                "k": [
                  -9.5,
                  80.5
                ],
                "ix": 2
              },
              "r": {
                "a": 0,
                "k": 0,
                "ix": 6
              },
              "sa": {
                "a": 0,
                "k": 0,
                "ix": 5
              },
              "o": {
                "a": 0,
                "k": 100,
                "ix": 7
              }
            }
          ]
        }
      ],
      "ind": 4
    }
  ],
  "v": "5.5.5",
  "fr": 100,
  "op": 302,
  "ip": 0,
  "assets": []
}